globalmart_api/__init__.py
GLOBALMART_FUNCTION_BDIST-0.1.dist-info/License.txt
GLOBALMART_FUNCTION_BDIST-0.1.dist-info/METADATA
GLOBALMART_FUNCTION_BDIST-0.1.dist-info/WHEEL
GLOBALMART_FUNCTION_BDIST-0.1.dist-info/top_level.txt
GLOBALMART_FUNCTION_BDIST-0.1.dist-info/RECORD
