Metadata-Version: 2.1
Name: GLOBALMART-FUNCTION-BDIST
Version: 0.1
Summary: Testing installation of Package
Author: Nishpa Vanapalli
Author-email: nishpa.vanapalli@fractal.ai
License: MIT
License-File: License.txt
Requires-Dist: pandas
